bulk_chain/__init__.py
bulk_chain/api.py
bulk_chain/core/__init__.py
bulk_chain/core/llm_base.py
bulk_chain/core/service_asyncio.py
bulk_chain/core/service_batch.py
bulk_chain/core/service_data.py
bulk_chain/core/service_dict.py
bulk_chain/core/service_json.py
bulk_chain/core/service_schema.py
bulk_chain/core/utils.py
bulk_chain-1.1.0.dist-info/LICENSE
bulk_chain-1.1.0.dist-info/METADATA
bulk_chain-1.1.0.dist-info/WHEEL
bulk_chain-1.1.0.dist-info/top_level.txt
bulk_chain-1.1.0.dist-info/RECORD
