Metadata-Version: 2.1
Name: bulk_chain
Version: 1.1.0
Summary: A lightweight, no-strings-attached Chain-of-Thought framework for your LLM, ensuring reliable results for bulk input requests.
Home-page: https://github.com/nicolay-r/bulk-chain
Author: Nicolay Rusnachenko
Author-email: rusnicolay@gmail.com
License: MIT License
Keywords: natural language processing,chain-of-thought,reasoning
Classifier: Programming Language :: Python
Classifier: Programming Language :: Python :: 3.9
Classifier: Topic :: Software Development :: Libraries :: Python Modules
Classifier: Topic :: Scientific/Engineering :: Information Analysis
Classifier: Topic :: Text Processing :: Linguistic
Requires-Python: >=3.6
License-File: LICENSE
